{"key":"吳順子","label":"","bundle":{"title":"허단 (許鍛)","leftLines":["오순자 (吳順子) · 배우자: 허단 (許鍛)","夫父: 허진철 (許鎭澈) · 夫母: 김화자 (金華子)","자녀: [31세손]","장남 허성영 (許成寧)","차남 허성민 (許成䪸)"],"rightLines":["30세손 [許鎭澈系, 許炳四男]","허단(許鍛, 許鎭澈長男, 母 金華子, 허진철장남) - 오순자(吳順子, 配)","허관(許錧, 許鎭澈貳男, 母 金華子, 허진철차남) - 박하순(朴河順, 配)","허영선(許英仙, 許鎭澈長女, 母 車任濬, 허진철장녀) - 권혁풍(權赫風, 配)","허영신(許英信, 許鎭澈貳女, 母 車任濬, 허진철차녀) - 전기호(全機鎬, 配)","허영복(許英福, 許鎭澈參男, 母 車任濬, 허진철삼남) - 김대중(金大中, 配)","허영란(許英蘭, 許鎭澈參女, 母 車任濬, 허진철삼녀) - 사성엽(史星燁, 配)","허동(許東, 許鎭澈四男, 母 車任濬, 허진철사남)","31세손 [許鍛系, 許鎭澈長男]","허성영(許成寧, 許鍛長男, 母 吳順子, 허단장남)","허성민(許成䪸, 許鍛貳男, 母 吳順子, 허단차남)"],"ancestorLines":["祖父: 허병 (許炳) [28세손] · 祖母: 이병주 (李炳州)","父親: 허진철 (許鎭澈) [29세손] · 母親: 김화자 (金華子)"]}}